tracardi_mysql_connector/plugin.py
tracardi_mysql_connector/model/configuration.py
tracardi_mysql_connector/model/connection.py
tracardi_mysql_connector/model/__pycache__/configuration.cpython-37.pyc
tracardi_mysql_connector/model/__pycache__/configuration.cpython-38.pyc
tracardi_mysql_connector/model/__pycache__/connection.cpython-37.pyc
tracardi_mysql_connector/model/__pycache__/connection.cpython-38.pyc
tracardi_mysql_connector-0.6.0.dist-info/LICENSE.md
tracardi_mysql_connector-0.6.0.dist-info/METADATA
tracardi_mysql_connector-0.6.0.dist-info/WHEEL
tracardi_mysql_connector-0.6.0.dist-info/top_level.txt
tracardi_mysql_connector-0.6.0.dist-info/RECORD
